starlette_zipkin/__init__.py
starlette_zipkin/config.py
starlette_zipkin/middleware.py
starlette_zipkin/trace.py
starlette_zipkin/header_formatters/__init__.py
starlette_zipkin/header_formatters/b3.py
starlette_zipkin/header_formatters/template.py
starlette_zipkin/header_formatters/uber.py
starlette_zipkin-0.3.0.dist-info/METADATA
starlette_zipkin-0.3.0.dist-info/WHEEL
starlette_zipkin-0.3.0.dist-info/top_level.txt
starlette_zipkin-0.3.0.dist-info/RECORD
