Metadata-Version: 2.1
Name: starlette-zipkin
Version: 0.3.0
Summary: Zipkin integration for ASGI frameworks.
Home-page: https://github.com/mchlvl/starlette_zipkin
Author: Michal Vala
Author-email: mic.vala@gmail.com
License: BSD
Classifier: Development Status :: 3 - Alpha
Classifier: Environment :: Web Environment
Classifier: Intended Audience :: Developers
Classifier: License :: OSI Approved :: BSD License
Classifier: Operating System :: OS Independent
Classifier: Topic :: Internet :: WWW/HTTP
Classifier: Programming Language :: Python :: 3
Classifier: Programming Language :: Python :: 3.7
Requires-Dist: aiozipkin (<2)
Requires-Dist: starlette (<21,>0.14)
